examples/V1/append/noaa-cdr-sst.ipynb
examples/V1/coiled/terraclimate.ipynb
examples/V1/mursst-icechunk-with-lithops/Dockerfile
examples/V1/mursst-icechunk-with-lithops/README.md
examples/V1/mursst-icechunk-with-lithops/__init__.py
examples/V1/mursst-icechunk-with-lithops/cli.py
examples/V1/mursst-icechunk-with-lithops/config.py
examples/V1/mursst-icechunk-with-lithops/helpers.py
examples/V1/mursst-icechunk-with-lithops/lithops.yaml
examples/V1/mursst-icechunk-with-lithops/lithops_functions.py
examples/V1/mursst-icechunk-with-lithops/main.py
examples/V1/mursst-icechunk-with-lithops/models.py
examples/V1/mursst-icechunk-with-lithops/repo.py
examples/V1/mursst-icechunk-with-lithops/requirements.txt
examples/V1/mursst-icechunk-with-lithops/url_utils.py
examples/V1/mursst-icechunk-with-lithops/virtual_datasets.py
examples/V1/mursst-icechunk-with-lithops/zarr_operations.py
examples/V1/mursst-icechunk-with-lithops/ec2_for_lithops_runtime/00-create-security-group.sh
examples/V1/mursst-icechunk-with-lithops/ec2_for_lithops_runtime/01-launch-ec2.sh
examples/V1/mursst-icechunk-with-lithops/ec2_for_lithops_runtime/02-setup-ec2-role.sh
examples/V1/mursst-icechunk-with-lithops/ec2_for_lithops_runtime/03-setup-ec2.sh
examples/V1/mursst-icechunk-with-lithops/ec2_for_lithops_runtime/README.md
examples/V1/oae/Dockerfile
examples/V1/oae/README.md
examples/V1/virtualizarr-with-lithops/Dockerfile_virtualizarr
examples/V1/virtualizarr-with-lithops/README.md
examples/V1/virtualizarr-with-lithops/lithops.yaml
examples/V1/virtualizarr-with-lithops/requirements.txt
examples/V1/virtualizarr-with-lithops/virtualizarr-with-lithops.py
examples/V2/README.md
examples/V2/goes_basic.py
examples/V2/goes_with_caching_stores.py
virtualizarr/__init__.py
virtualizarr/accessor.py
virtualizarr/codecs.py
virtualizarr/parallel.py
virtualizarr/py.typed
virtualizarr/registry.py
virtualizarr/utils.py
virtualizarr/xarray.py
virtualizarr/manifests/__init__.py
virtualizarr/manifests/array.py
virtualizarr-2.4.0.dist-info/licenses/LICENSE
virtualizarr-2.4.0.dist-info/METADATA
virtualizarr-2.4.0.dist-info/WHEEL
virtualizarr-2.4.0.dist-info/top_level.txt
virtualizarr-2.4.0.dist-info/RECORD
