Metadata-Version: 2.4
Name: virtualizarr
Version: 2.4.0
Summary: Create virtual Zarr stores from archival data using xarray API
Author-email: Tom Nicholas <tom@earthmover.io>, Max Jones <max@developmentseed.org>, Raphael Hagen <raphael@carbonplan.org>
License-Expression: Apache-2.0
Project-URL: Home, https://github.com/zarr-developers/VirtualiZarr
Project-URL: Documentation, https://github.com/zarr-developers/VirtualiZarr/blob/main/README.md
Classifier: Development Status :: 3 - Alpha
Classifier: Intended Audience :: Science/Research
Classifier: Topic :: Scientific/Engineering
Classifier: Operating System :: OS Independent
Classifier: Programming Language :: Python
Classifier: Programming Language :: Python :: 3.11
Classifier: Programming Language :: Python :: 3.12
Classifier: Programming Language :: Python :: 3.13
Requires-Python: >=3.11
License-File: LICENSE
Requires-Dist: xarray>=2025.03.0
Requires-Dist: numpy>=2.0.0
Requires-Dist: universal-pathlib
Requires-Dist: numcodecs>=0.15.1
Requires-Dist: ujson
Requires-Dist: packaging
Requires-Dist: zarr>=3.1.0
Requires-Dist: obstore>=0.7.0
Requires-Dist: obspec_utils>=0.7.0
Provides-Extra: remote
Requires-Dist: fsspec; extra == "remote"
Requires-Dist: requests; extra == "remote"
Requires-Dist: aiohttp; extra == "remote"
Requires-Dist: s3fs; extra == "remote"
Provides-Extra: hdf
Requires-Dist: h5py; extra == "hdf"
Requires-Dist: hdf5plugin; extra == "hdf"
Requires-Dist: imagecodecs; extra == "hdf"
Requires-Dist: imagecodecs-numcodecs==2024.6.1; extra == "hdf"
Provides-Extra: netcdf3
Requires-Dist: virtualizarr[remote]; extra == "netcdf3"
Requires-Dist: kerchunk>=0.2.8; extra == "netcdf3"
Requires-Dist: scipy; extra == "netcdf3"
Provides-Extra: fits
Requires-Dist: virtualizarr[remote]; extra == "fits"
Requires-Dist: kerchunk>=0.2.8; extra == "fits"
Requires-Dist: astropy; extra == "fits"
Provides-Extra: tiff
Requires-Dist: virtual-tiff; extra == "tiff"
Provides-Extra: kerchunk-parquet
Requires-Dist: virtualizarr[remote]; extra == "kerchunk-parquet"
Requires-Dist: fastparquet; extra == "kerchunk-parquet"
Provides-Extra: all-parsers
Requires-Dist: virtualizarr[hdf]; extra == "all-parsers"
Requires-Dist: virtualizarr[netcdf3]; extra == "all-parsers"
Requires-Dist: virtualizarr[fits]; extra == "all-parsers"
Requires-Dist: virtualizarr[kerchunk_parquet]; extra == "all-parsers"
Requires-Dist: virtualizarr[tiff]; extra == "all-parsers"
Provides-Extra: icechunk
Requires-Dist: icechunk>=1.1.2; extra == "icechunk"
Provides-Extra: kerchunk
Requires-Dist: fastparquet; extra == "kerchunk"
Provides-Extra: all-writers
Requires-Dist: virtualizarr[icechunk]; extra == "all-writers"
Requires-Dist: virtualizarr[kerchunk]; extra == "all-writers"
Dynamic: license-file
